{
  "Address": "AccountId",
  "LookupSource": "AccountId",
  "AuctionId": "u64",
  "ClassId": "u64",
  "TokenId": "u64",
  "ClassData": "u32",
  "TokenData": "u32",
  "CID": "Vec<u8>",
  "ClassInfo": {
    "metadata": "Vec<u8>",
    "total_issuance": "TokenId",
    "owner": "AccountId",
    "data": "ClassData"
  },
  "TokenInfo": {
    "metadata": "Vec<u8>",
    "owner": "AccountId",
    "data": "TokenData"
  },
  "ClassInfoOf": "ClassInfo",
  "TokenInfoOf": "TokenInfo",
  "AuctionType": {
    "_enum": [
      "English",
      "Candle",
      "Dutch",
      "TopUp",
      "FixedSwap"
    ]
  },
  "AuctionInfo": {
    "name": "Vec<u8>",
    "owner": "AccountId",
    "last_bid": "Option<(AccountId, Balance)>",
    "start": "BlockNumber",
    "end": "BlockNumber",
    "auction_type": "AuctionType",
    "token_id": "(u64, u64)",
    "no_identity_allowed": "bool",
    "starting_price": "Balance",
    "private": "bool",
    "max_participants": "u32",
    "minimal_bid": "Balance"
  },
  "AuctionInfoOf": "AuctionInfo"
}